xontrib/argcomplete.py
xontrib_argcomplete-0.3.4.dist-info/LICENSE
xontrib_argcomplete-0.3.4.dist-info/METADATA
xontrib_argcomplete-0.3.4.dist-info/WHEEL
xontrib_argcomplete-0.3.4.dist-info/top_level.txt
xontrib_argcomplete-0.3.4.dist-info/RECORD
