Metadata-Version: 2.1
Name: xontrib-argcomplete
Version: 0.3.4
Summary: Argcomplete support for python and xonsh scripts in xonsh shell. 
Home-page: https://github.com/anki-code/xontrib-argcomplete
Author: anki-code
Author-email: xonsh@googlegroups.com
License: BSD
Project-URL: Documentation, https://github.com/anki-code/xontrib-argcomplete/blob/master/README.md
Project-URL: Code, https://github.com/anki-code/xontrib-argcomplete
Project-URL: Issue tracker, https://github.com/anki-code/xontrib-argcomplete/issues
Platform: any
Classifier: Environment :: Console
Classifier: Intended Audience :: End Users/Desktop
Classifier: Operating System :: OS Independent
Classifier: Programming Language :: Python
Classifier: Programming Language :: Unix Shell
Classifier: Topic :: System :: Shells
Classifier: Topic :: System :: System Shells
Classifier: Topic :: Terminals
Classifier: Topic :: System :: Networking
Classifier: License :: OSI Approved :: BSD License
Requires-Python: >=3.6
License-File: LICENSE
Requires-Dist: xonsh>=0.12.1
